stax/__init__.py
stax/exceptions.py
stax/gitlib.py
stax/stax.py
stax/utils.py
stax/aws/__init__.py
stax/aws/cloudformation.py
stax/aws/confirm.py
stax/aws/connection_manager.py
stax/commands/__init__.py
stax/commands/cmd_delete.py
stax/commands/cmd_edit.py
stax/commands/cmd_generate.py
stax/commands/cmd_peer.py
stax/commands/cmd_pull.py
stax/commands/cmd_push.py
stax/commands/cmd_summary.py
stax-0.4.2.dist-info/LICENSE
stax-0.4.2.dist-info/METADATA
stax-0.4.2.dist-info/WHEEL
stax-0.4.2.dist-info/entry_points.txt
stax-0.4.2.dist-info/top_level.txt
stax-0.4.2.dist-info/RECORD
